examples/selenium_examples.py
local/captcha_test.py
local/search.py
pyselsearch/__init__.py
pyselsearch/cli.py
pyselsearch/core.py
pyselsearch/proxy_gen.py
pyselsearch-0.2.2.dist-info/licenses/LICENSE
pyselsearch-0.2.2.dist-info/METADATA
pyselsearch-0.2.2.dist-info/WHEEL
pyselsearch-0.2.2.dist-info/entry_points.txt
pyselsearch-0.2.2.dist-info/top_level.txt
pyselsearch-0.2.2.dist-info/RECORD
