Metadata-Version: 2.4
Name: pyselsearch
Version: 0.2.2
Summary: Just another side project, to help my personal issue of google searching
Author-email: Jisan <md7509jisan@gmail.com>
License: MIT
Project-URL: Homepage, https://github.com/jisan09/pyselsearch
Project-URL: Repository, https://github.com/jisan09/pyselsearch
Project-URL: Issues, https://github.com/jisan09/pyselsearch/issues
Classifier: Programming Language :: Python :: 3
Classifier: License :: OSI Approved :: MIT License
Classifier: Operating System :: OS Independent
Classifier: Development Status :: 3 - Alpha
Classifier: Intended Audience :: Developers
Classifier: Topic :: Internet :: WWW/HTTP :: Indexing/Search
Requires-Python: >=3.10
License-File: LICENSE
Requires-Dist: seleniumbase==4.40.8
Provides-Extra: dev
Requires-Dist: pytest; extra == "dev"
Requires-Dist: pytest-mock; extra == "dev"
Requires-Dist: ruff; extra == "dev"
Requires-Dist: black; extra == "dev"
Requires-Dist: isort; extra == "dev"
Dynamic: license-file
